depscripter/__init__.py
depscripter/__main__.py
depscripter/cli.py
depscripter/injector.py
depscripter/resolver.py
depscripter/scanner.py
depscripter-0.2.0.dist-info/METADATA
depscripter-0.2.0.dist-info/WHEEL
depscripter-0.2.0.dist-info/entry_points.txt
depscripter-0.2.0.dist-info/licenses/LICENSE
depscripter-0.2.0.dist-info/RECORD
