Metadata-Version: 2.4
Name: depscripter
Version: 0.2.0
Summary: A zero-dependency tool to add PEP 723 metadata to Python scripts.
Project-URL: Homepage, https://github.com/seanhoward/depscripter
Project-URL: Issues, https://github.com/seanhoward/depscripter/issues
Author-email: Sean Howard <sean@example.com>
License-File: LICENSE
Keywords: dependencies,metadata,pep-723,python,script
Classifier: Development Status :: 4 - Beta
Classifier: Intended Audience :: Developers
Classifier: License :: OSI Approved :: MIT License
Classifier: Programming Language :: Python :: 3
Classifier: Programming Language :: Python :: 3.8
Classifier: Programming Language :: Python :: 3.9
Classifier: Programming Language :: Python :: 3.10
Classifier: Programming Language :: Python :: 3.11
Classifier: Programming Language :: Python :: 3.12
Requires-Python: >=3.8
